{"stkNo": "6287", "stkName": "\u5143\u9686            ", "showListPriceNote": false, "showListPriceLink": false, "reportDate": "113/02", "iTotalRecords": 13, "aaData": [["113/02/01", "3", "48", "15.50", "15.75", "15.50", "15.75", "0.30", "5"], ["113/02/02", "0", "0", "--", "--", "--", "--", "0.00", "0"], ["113/02/05", "2", "33", "14.95", "14.95", "14.95", "14.95", "-0.80", "6"], ["113/02/15", "10", "151", "15.05", "15.05", "15.00", "15.05", "0.10", "6"], ["113/02/16", "4", "59", "14.35", "15.75", "14.35", "15.75", "0.70", "5"], ["113/02/19", "5", "83", "15.65", "15.95", "15.65", "15.95", "0.20", "14"], ["113/02/20", "0", "1", "--", "--", "--", "--", "0.00", "1"], ["113/02/21", "10", "163", "15.75", "16.00", "15.75", "16.00", "0.05", "9"], ["113/02/22", "4", "64", "16.00", "16.00", "15.55", "16.00", "0.00", "5"], ["113/02/23", "15", "240", "15.40", "16.95", "15.40", "16.55", "0.55", "19"], ["113/02/26", "0", "4", "--", "--", "--", "--", "0.00", "1"], ["113/02/27", "0", "1", "--", "--", "--", "--", "0.00", "4"], ["113/02/29", "2", "37", "15.80", "17.35", "15.80", "17.35", "0.80", "7"]], "fields": ["\u65e5\u671f", "\u6210\u4ea4\u80a1\u6578", "\u6210\u4ea4\u91d1\u984d", "\u958b\u76e4\u50f9", "\u6700\u9ad8\u50f9", "\u6700\u4f4e\u50f9", "\u6536\u76e4\u50f9", "\u6f32\u8dcc\u50f9\u5dee", "\u6210\u4ea4\u7b46\u6578"], "data": [["113/02/01", "3", "48", "15.50", "15.75", "15.50", "15.75", "0.30", "5"], ["113/02/02", "0", "0", "--", "--", "--", "--", "0.00", "0"], ["113/02/05", "2", "33", "14.95", "14.95", "14.95", "14.95", "-0.80", "6"], ["113/02/15", "10", "151", "15.05", "15.05", "15.00", "15.05", "0.10", "6"], ["113/02/16", "4", "59", "14.35", "15.75", "14.35", "15.75", "0.70", "5"], ["113/02/19", "5", "83", "15.65", "15.95", "15.65", "15.95", "0.20", "14"], ["113/02/20", "0", "1", "--", "--", "--", "--", "0.00", "1"], ["113/02/21", "10", "163", "15.75", "16.00", "15.75", "16.00", "0.05", "9"], ["113/02/22", "4", "64", "16.00", "16.00", "15.55", "16.00", "0.00", "5"], ["113/02/23", "15", "240", "15.40", "16.95", "15.40", "16.55", "0.55", "19"], ["113/02/26", "0", "4", "--", "--", "--", "--", "0.00", "1"], ["113/02/27", "0", "1", "--", "--", "--", "--", "0.00", "4"], ["113/02/29", "2", "37", "15.80", "17.35", "15.80", "17.35", "0.80", "7"]], "stat": "OK"}